twitter_ads_v2/__init__.py
twitter_ads_v2/base.py
twitter_ads_v2/client.py
twitter_ads_v2/enum.py
twitter_ads_v2/error.py
twitter_ads_v2/http.py
twitter_ads_v2/oauth.py
twitter_ads_v2/resources.py
twitter_ads_v2/utils.py
twitter_ads_v2-0.1.1.dist-info/LICENSE
twitter_ads_v2-0.1.1.dist-info/METADATA
twitter_ads_v2-0.1.1.dist-info/WHEEL
twitter_ads_v2-0.1.1.dist-info/top_level.txt
twitter_ads_v2-0.1.1.dist-info/RECORD
