Metadata-Version: 2.1
Name: twitter-ads-v2
Version: 0.1.1
Summary: Twitter Ads API SDK for Python.
Home-page: https://github.com/smaeda-ks/twitter-python-ads-sdk-v2
Author: Shohei Maeda
License: MIT
Download-URL: https://github.com/smaeda-ks/twitter-python-ads-sdk-v2/tarball/master
Platform: any
Classifier: Development Status :: 5 - Production/Stable
Classifier: Intended Audience :: Developers
Classifier: License :: OSI Approved :: MIT License
Classifier: Operating System :: OS Independent
Classifier: Programming Language :: Python
Classifier: Programming Language :: Python :: 3
Classifier: Programming Language :: Python :: 3.5
Classifier: Programming Language :: Python :: 3.6
Classifier: Programming Language :: Python :: 3.7
Classifier: Programming Language :: Python :: Implementation :: CPython
Classifier: Programming Language :: Python :: Implementation :: PyPy
Classifier: Topic :: Internet
Classifier: Topic :: Internet :: WWW/HTTP
Classifier: Topic :: Software Development :: Libraries :: Python Modules
Requires-Dist: python-dateutil
Requires-Dist: oauthlib (==3.1.0)
Requires-Dist: requests
Provides-Extra: doc
Requires-Dist: sphinx (<3.0.0,>=2.0.0) ; extra == 'doc'
Requires-Dist: sphinx-rtd-theme ; extra == 'doc'
Requires-Dist: m2r ; extra == 'doc'
